Workbook

Sheet Read me
A1: Paper LBO: independent reference
A2: FICTIONAL DEMONSTRATION DATA. NOT AN EXCHANGE FILING.
A3: Units | B3: All monetary values in INR crore. Shares are absolute units.
A4: How to use | B4: Edit Inputs, then recalculate in Excel. Ten forecast years support hold periods 1 to 10.
A5: Economics | B5: Opening debt interest; mandatory repayment then cash sweep; no interim dividends.
A6: Risk | B6: Funding shortfalls invalidate returns. No assumption is a financing offer.
A7: Sensitivity | B7: Current scenario snapshots. Re-export after changing browser assumptions.
A8: Caveats | B8: Revenue denominator used for inventory/payable days. Tax rate is an editable scenario.

Sheet Inputs
A1: Editable assumptions | B1: Paper LBO: independent reference
A2: Amounts in INR crore | B2: Rates are decimal percentages
A3: Entry multiple | B3: 8
A4: Exit multiple | B4: 8
A5: Leverage cap | B5: 0
A6: Interest rate | B6: 0.11
A7: Tax rate | B7: 0
A8: Cash sweep | B8: 0.75
A9: Hold years | B9: 5
A10: Transaction fees | B10: 0
A11: Revenue growth | B11: 0
A12: Total margin expansion | B12: 0
A13: Capex / revenue | B13: 0
A14: Depreciation / revenue | B14: 0.025
... A18: Hurdle IRR | B18: 0.2
A19: Base financials | B19: Source: Historical and Evidence
A20: Normalized entry EBITDA | B20: =Historical!F4+SUM(Historical!F19:F35) -> 200
A21: Base revenue | B21: =Historical!F3 -> 1000
A22: Existing debt | B22: =Historical!F16 -> 100
A23: Existing cash | B23: =Historical!F15 -> 50
A24: Base year | B24: 2026

Sheet Historical
A1: Historical financials | B1: INR crore
A2: Financial year | B2: 2022 | C2: 2023 | D2: 2024 | E2: 2025 | F2: 2026
A3: revenue | B3: 1000 | C3: 1000 | D3: 1000 | E3: 1000 | F3: 1000
A4: ebitda | B4: 200 | C4: 200 | D4: 200 | E4: 200 | F4: 200
A5: depreciation | B5: 25 | C5: 25 | D5: 25 | E5: 25 | F5: 25
A6: interest | B6: 12 | C6: 12 | D6: 12 | E6: 12 | F6: 12
A7: taxPaid | B7: 40 | C7: 40 | D7: 40 | E7: 40 | F7: 40
A8: pat | B8: 123 | C8: 123 | D8: 123 | E8: 123 | F8: 123
A9: receivables | B9: 120 | C9: 120 | D9: 120 | E9: 120 | F9: 120
A10: inventory | B10: 130 | C10: 130 | D10: 130 | E10: 130 | F10: 130
A11: payables | B11: 70 | C11: 70 | D11: 70 | E11: 70 | F11: 70
A12: capex | B12: 40 | C12: 40 | D12: 40 | E12: 40 | F12: 40
A15: cash | B15: 50 | C15: 50 | D15: 50 | E15: 50 | F15: 50
... A18: shares | B18: 100000000 | C18: 100000000 | D18: 100000000 | E18: 100000000 | F18: 100000000

Sheet Sources & uses
A1: Transaction funding | B1: INR crore
A2: No double-counting target cash | B2: Existing debt fully refinanced
A3: Entry enterprise value | B3: =Inputs!B20*Inputs!B3 -> 1600
A4: Transaction fees | B4: =B3*Inputs!B10 -> 0
A5: New debt | B5: =MIN(Inputs!B20*Inputs!B5,Inputs!B20/(Inputs!B6*Inputs!B17)) -> 0
A6: Purchase equity | B6: =B3-Inputs!B22+Inputs!B23 -> 1550
A7: Refinanced existing debt | B7: =Inputs!B22 -> 100
A8: Target cash funding | B8: =Inputs!B23 -> 50
A9: Total uses | B9: =B6+B7+B4 -> 1650
A10: Sponsor equity | B10: =B9-B5-B8 -> 1600
A11: Sources less uses | B11: =B5+B8+B10-B9 -> 0

Sheet Projection
A1: Cash and debt schedule | B1: All ten years recalculate; hold selects the exit year
A2: Financial year | B2: 2027 | C2: 2028 | D2: 2029 | E2: 2030 | F2: 2031 | G2: 2032 | H2: 2033 | I2: 2034 | J2: 2035 | K2: 2036
A3: Revenue | B3: =Inputs!B21*(1+Inputs!B11)^1 -> 1000 | C3: =Inputs!B21*(1+Inputs!B11)^2 -> 1000 | D3: =Inputs!B21*(1+Inputs!B11)^3 -> 1000 | E3: =Inputs!B21*(1+Inputs!B11)^4 -> 1000 | F3: =Inputs!B21*(1+Inputs!B11)^5 -> 1000 | G3: =Inputs!B21*(1+Inputs!B11)^6 -> 1000 | H3: =Inputs!B21*(1+Inputs!B11)^7 -> 1000 | I3: =Inputs!B21*(1+Inputs!B11)^8 -> 1000 | J3: =Inputs!B21*(1+Inputs!B11)^9 -> 1000 | K3: =Inputs!B21*(1+Inputs!B11)^10 -> 1000
A4: EBITDA | B4: =B3*(Inputs!B20/Inputs!B21+Inputs!B12*1/Inputs!B9) -> 200 | C4: =C3*(Inputs!B20/Inputs!B21+Inputs!B12*2/Inputs!B9) -> 200 | D4: =D3*(Inputs!B20/Inputs!B21+Inputs!B12*3/Inputs!B9) -> 200 | E4: =E3*(Inputs!B20/Inputs!B21+Inputs!B12*4/Inputs!B9) -> 200 | F4: =F3*(Inputs!B20/Inputs!B21+Inputs!B12*5/Inputs!B9) -> 200 | G4: =G3*(Inputs!B20/Inputs!B21+Inputs!B12*6/Inputs!B9) -> 200 | H4: =H3*(Inputs!B20/Inputs!B21+Inputs!B12*7/Inputs!B9) -> 200 | I4: =I3*(Inputs!B20/Inputs!B21+Inputs!B12*8/Inputs!B9) -> 200 | J4: =J3*(Inputs!B20/Inputs!B21+Inputs!B12*9/Inputs!B9) -> 200 | K4: =K3*(Inputs!B20/Inputs!B21+Inputs!B12*10/Inputs!B9) -> 200
A5: Depreciation | B5: =B3*Inputs!B14 -> 25 | C5: =C3*Inputs!B14 -> 25 | D5: =D3*Inputs!B14 -> 25 | E5: =E3*Inputs!B14 -> 25 | F5: =F3*Inputs!B14 -> 25 | G5: =G3*Inputs!B14 -> 25 | H5: =H3*Inputs!B14 -> 25 | I5: =I3*Inputs!B14 -> 25 | J5: =J3*Inputs!B14 -> 25 | K5: =K3*Inputs!B14 -> 25
A6: Opening debt | B6: ='Sources & uses'!B5 -> 0 | C6: =B14 -> 0 | D6: =C14 -> 0 | E6: =D14 -> 0 | F6: =E14 -> 0 | G6: =F14 -> 0 | H6: =G14 -> 0 | I6: =H14 -> 0 | J6: =I14 -> 0 | K6: =J14 -> 0
A7: Cash interest | B7: =B6*Inputs!B6 -> 0 | C7: =C6*Inputs!B6 -> 0 | D7: =D6*Inputs!B6 -> 0 | E7: =E6*Inputs!B6 -> 0 | F7: =F6*Inputs!B6 -> 0 | G7: =G6*Inputs!B6 -> 0 | H7: =H6*Inputs!B6 -> 0 | I7: =I6*Inputs!B6 -> 0 | J7: =J6*Inputs!B6 -> 0 | K7: =K6*Inputs!B6 -> 0
A8: Cash tax | B8: =MAX(0,B4-B5-B7)*Inputs!B7 -> 0 | C8: =MAX(0,C4-C5-C7)*Inputs!B7 -> 0 | D8: =MAX(0,D4-D5-D7)*Inputs!B7 -> 0 | E8: =MAX(0,E4-E5-E7)*Inputs!B7 -> 0 | F8: =MAX(0,F4-F5-F7)*Inputs!B7 -> 0 | G8: =MAX(0,G4-G5-G7)*Inputs!B7 -> 0 | H8: =MAX(0,H4-H5-H7)*Inputs!B7 -> 0 | I8: =MAX(0,I4-I5-I7)*Inputs!B7 -> 0 | J8: =MAX(0,J4-J5-J7)*Inputs!B7 -> 0 | K8: =MAX(0,K4-K5-K7)*Inputs!B7 -> 0
A9: Capex | B9: =B3*Inputs!B13 -> 0 | C9: =C3*Inputs!B13 -> 0 | D9: =D3*Inputs!B13 -> 0 | E9: =E3*Inputs!B13 -> 0 | F9: =F3*Inputs!B13 -> 0 | G9: =G3*Inputs!B13 -> 0 | H9: =H3*Inputs!B13 -> 0 | I9: =I3*Inputs!B13 -> 0 | J9: =J3*Inputs!B13 -> 0 | K9: =K3*Inputs!B13 -> 0
A10: Increase in working capital | B10: =(B3-Inputs!B21)*Inputs!B15 -> 0 | C10: =(C3-B3)*Inputs!B15 -> 0 | D10: =(D3-C3)*Inputs!B15 -> 0 | E10: =(E3-D3)*Inputs!B15 -> 0 | F10: =(F3-E3)*Inputs!B15 -> 0 | G10: =(G3-F3)*Inputs!B15 -> 0 | H10: =(H3-G3)*Inputs!B15 -> 0 | I10: =(I3-H3)*Inputs!B15 -> 0 | J10: =(J3-I3)*Inputs!B15 -> 0 | K10: =(K3-J3)*Inputs!B15 -> 0
A11: Free cash flow after interest | B11: =B4-B7-B8-B9-B10 -> 200 | C11: =C4-C7-C8-C9-C10 -> 200 | D11: =D4-D7-D8-D9-D10 -> 200 | E11: =E4-E7-E8-E9-E10 -> 200 | F11: =F4-F7-F8-F9-F10 -> 200 | G11: =G4-G7-G8-G9-G10 -> 200 | H11: =H4-H7-H8-H9-H10 -> 200 | I11: =I4-I7-I8-I9-I10 -> 200 | ... K11: =K4-K7-K8-K9-K10 -> 200
A12: Mandatory repayment | B12: =MIN(B6,'Sources & uses'!B5*Inputs!B16) -> 0 | C12: =MIN(C6,'Sources & uses'!B5*Inputs!B16) -> 0 | D12: =MIN(D6,'Sources & uses'!B5*Inputs!B16) -> 0 | E12: =MIN(E6,'Sources & uses'!B5*Inputs!B16) -> 0 | F12: =MIN(F6,'Sources & uses'!B5*Inputs!B16) -> 0 | G12: =MIN(G6,'Sources & uses'!B5*Inputs!B16) -> 0 | H12: =MIN(H6,'Sources & uses'!B5*Inputs!B16) -> 0 | I12: =MIN(I6,'Sources & uses'!B5*Inputs!B16) -> 0 | J12: =MIN(J6,'Sources & uses'!B5*Inputs!B16) -> 0 | K12: =MIN(K6,'Sources & uses'!B5*Inputs!B16) -> 0
A13: Cash sweep | B13: =MIN(B6-B12,MAX(0,B11-B12)*Inputs!B8) -> 0 | C13: =MIN(C6-C12,MAX(0,C11-C12)*Inputs!B8) -> 0 | D13: =MIN(D6-D12,MAX(0,D11-D12)*Inputs!B8) -> 0 | E13: =MIN(E6-E12,MAX(0,E11-E12)*Inputs!B8) -> 0 | F13: =MIN(F6-F12,MAX(0,F11-F12)*Inputs!B8) -> 0 | G13: =MIN(G6-G12,MAX(0,G11-G12)*Inputs!B8) -> 0 | H13: =MIN(H6-H12,MAX(0,H11-H12)*Inputs!B8) -> 0 | I13: =MIN(I6-I12,MAX(0,I11-I12)*Inputs!B8) -> 0 | J13: =MIN(J6-J12,MAX(0,J11-J12)*Inputs!B8) -> 0 | K13: =MIN(K6-K12,MAX(0,K11-K12)*Inputs!B8) -> 0
A14: Closing debt | B14: =MAX(0,B6-B12-B13) -> 0 | C14: =MAX(0,C6-C12-C13) -> 0 | D14: =MAX(0,D6-D12-D13) -> 0 | E14: =MAX(0,E6-E12-E13) -> 0 | F14: =MAX(0,F6-F12-F13) -> 0 | G14: =MAX(0,G6-G12-G13) -> 0 | H14: =MAX(0,H6-H12-H13) -> 0 | I14: =MAX(0,I6-I12-I13) -> 0 | ... K14: =MAX(0,K6-K12-K13) -> 0
A15: Opening cash | B15: =0 -> 0 | C15: =B17 -> 200 | D15: =C17 -> 400 | E15: =D17 -> 600 | F15: =E17 -> 800 | G15: =F17 -> 1000 | H15: =G17 -> 1200 | I15: =H17 -> 1400 | J15: =I17 -> 1600 | K15: =J17 -> 1800
A16: Funding shortfall | B16: =MAX(0,B12-B11-B15) -> 0 | C16: =MAX(0,C12-C11-C15) -> 0 | D16: =MAX(0,D12-D11-D15) -> 0 | E16: =MAX(0,E12-E11-E15) -> 0 | F16: =MAX(0,F12-F11-F15) -> 0 | G16: =MAX(0,G12-G11-G15) -> 0 | H16: =MAX(0,H12-H11-H15) -> 0 | I16: =MAX(0,I12-I11-I15) -> 0 | ... K16: =MAX(0,K12-K11-K15) -> 0
A17: Closing cash | B17: =MAX(0,B15-MAX(0,B12-B11))+MAX(0,B11-B12-B13) -> 200 | C17: =MAX(0,C15-MAX(0,C12-C11))+MAX(0,C11-C12-C13) -> 400 | D17: =MAX(0,D15-MAX(0,D12-D11))+MAX(0,D11-D12-D13) -> 600 | E17: =MAX(0,E15-MAX(0,E12-E11))+MAX(0,E11-E12-E13) -> 800 | F17: =MAX(0,F15-MAX(0,F12-F11))+MAX(0,F11-F12-F13) -> 1000 | G17: =MAX(0,G15-MAX(0,G12-G11))+MAX(0,G11-G12-G13) -> 1200 | H17: =MAX(0,H15-MAX(0,H12-H11))+MAX(0,H11-H12-H13) -> 1400 | I17: =MAX(0,I15-MAX(0,I12-I11))+MAX(0,I11-I12-I13) -> 1600 | ... K17: =MAX(0,K15-MAX(0,K12-K11))+MAX(0,K11-K12-K13) -> 2000
A18: Interest coverage | B18: =IF(B7=0,"Unlevered",B4/B7) -> Unlevered | C18: =IF(C7=0,"Unlevered",C4/C7) -> Unlevered | D18: =IF(D7=0,"Unlevered",D4/D7) -> Unlevered | E18: =IF(E7=0,"Unlevered",E4/E7) -> Unlevered | F18: =IF(F7=0,"Unlevered",F4/F7) -> Unlevered | G18: =IF(G7=0,"Unlevered",G4/G7) -> Unlevered | H18: =IF(H7=0,"Unlevered",H4/H7) -> Unlevered | I18: =IF(I7=0,"Unlevered",I4/I7) -> Unlevered | ... K18: =IF(K7=0,"Unlevered",K4/K7) -> Unlevered

Sheet Returns
A1: Sponsor returns | B1: INR crore
A2: Exit selected by hold years | B2: Unfunded models have no investment return
A3: Exit EBITDA | B3: =INDEX(Projection!B4:K4,1,Inputs!B9) -> 200
A4: Exit enterprise value | B4: =B3*Inputs!B4 -> 1600
A5: Exit debt | B5: =INDEX(Projection!B14:K14,1,Inputs!B9) -> 0
A6: Exit cash | B6: =INDEX(Projection!B17:K17,1,Inputs!B9) -> 1000
A7: Exit equity | B7: =MAX(0,B4-B5+B6) -> 2600
A8: Sponsor IRR | B8: =IF(B14>0,"Unfunded",IF(B7=0,-1,(B7/'Sources & uses'!B10)^(1/Inputs!B9)-1)) -> 0.10197229
A9: MOIC | B9: =IF(B14>0,"Unfunded",B7/'Sources & uses'!B10) -> 1.625
A10: EBITDA growth contribution | B10: =(B3-Inputs!B20)*Inputs!B3 -> 0
A11: Multiple contribution | B11: =(Inputs!B4-Inputs!B3)*B3 -> 0
A12: Net debt reduction | B12: ='Sources & uses'!B5-B5+B6 -> 1000
A13: Fees contribution | B13: =-'Sources & uses'!B4 -> 0
A14: Total funding shortfall | B14: =SUM(Projection!B16:INDEX(Projection!B16:K16,1,Inputs!B9)) -> 0
A15: Bridge reconciliation | B15: =SUM(B10:B13)+B16-(B7-'Sources & uses'!B10) -> 0
A16: Limited liability floor | B16: =MAX(0,-(B4-B5+B6)) -> 0

Sheet Sensitivity
A1: Entry vs exit multiple | B1: IRR snapshots at export assumptions
A2: Entry / exit | B2: 6 | C2: 7 | D2: 8 | E2: 9 | F2: 10
A3: 6 | B3: 0.12888132 | C3: 0.14869835 | D3: 0.16723532 | E3: 0.18466445 | F3: 0.20112443
A4: 7 | B4: 0.094608784 | C4: 0.11382418 | D4: 0.13179837 | E4: 0.14869835 | F4: 0.16465862
A5: 8 | B5: 0.065762757 | C5: 0.084471771 | D5: 0.10197229 | E5: 0.11842691 | F5: 0.13396658
A6: 9 | B6: 0.040950397 | C6: 0.059223841 | D6: 0.076316923 | E6: 0.092388464 | F6: 0.10756634
A7: 10 | B7: 0.019244876 | C7: 0.037137289 | D7: 0.053873952 | E7: 0.069610376 | F7: 0.084471771

Sheet Evidence
A1: Field-level evidence | B1: demo
A2: Field | B2: Year | C2: Filing | D2: Page | E2: Source | F2: Kind
A3: revenue | B3: 2022 | C3: paper-2022 | D3: 70 | E3: /methodology | F3: demo
A4: ebitda | B4: 2022 | C4: paper-2022 | D4: 71 | E4: /methodology | F4: demo
A5: depreciation | B5: 2022 | C5: paper-2022 | D5: 72 | E5: /methodology | F5: demo
A6: interest | B6: 2022 | C6: paper-2022 | D6: 73 | E6: /methodology | F6: demo
A7: taxPaid | B7: 2022 | C7: paper-2022 | D7: 74 | E7: /methodology | F7: demo
A8: pat | B8: 2022 | C8: paper-2022 | D8: 75 | E8: /methodology | F8: demo
A9: receivables | B9: 2022 | C9: paper-2022 | D9: 76 | E9: /methodology | F9: demo
A10: inventory | B10: 2022 | C10: paper-2022 | D10: 77 | E10: /methodology | F10: demo
A11: payables | B11: 2022 | C11: paper-2022 | D11: 78 | E11: /methodology | F11: demo
A12: capex | B12: 2022 | C12: paper-2022 | D12: 79 | E12: /methodology | F12: demo
A13: cash | B13: 2022 | C13: paper-2022 | D13: 80 | E13: /methodology | F13: demo
A14: debt | B14: 2022 | C14: paper-2022 | D14: 81 | E14: /methodology | F14: demo
... A72: shares | B72: 2026 | C72: paper-2026 | D72: 83 | E72: /methodology | F72: demo
A73: Accepted normalization adjustments
